MANIFEST.in
README.rst
setup.py
version.txt
micral_harmonic/__init__.py
micral_harmonic/micral_harmonic.py
micral_harmonic/version.txt
micral_harmonic.egg-info/PKG-INFO
micral_harmonic.egg-info/SOURCES.txt
micral_harmonic.egg-info/dependency_links.txt
micral_harmonic.egg-info/not-zip-safe
micral_harmonic.egg-info/requires.txt
micral_harmonic.egg-info/top_level.txt