Metadata-Version: 1.0
Name: micral-harmonic
Version: 2.0
Summary: Measurement tools of the harmonicity of the microstructure
Home-page: UNKNOWN
Author: Yann LEROY
Author-email: yann.leroy102@orange.fr
License: MIT
Platform: UNKNOWN
